{
  "publicId": "241d28b8",
  "wikipediaSlug": "Deepika_Prasain",
  "wikipediaId": "Q57893456",
  "name": "Chhakka Panja 3",
  "fullName": "Chhakka Panja 3",
  "profileSummary": "Chhakka Panja 3 is a Nepalese comedy film from 2018, directed by Deepa Shree Niraula, and produced by Deepa Shree Niraula, Deepak Raj Giri, Kedar Ghimire and Jeetu Nepal for Aama Sarswoti Movies. It is the third film of the Chhakka Panja series. The film tells the story of the daughter of a headmaster and popular news reporter who marries the rich and illiterate Raja, the son of a big politician of her village and tries to improve conditions at a government school but faces hurdles in her goal. The film met with positive response from critics and audience for its story, screenplay, social message, comedy and performance of the cast especially of Kedar Ghimire. The film was a massive blockbuster at the box office breaking several and surpassing its predecessor Chhakka Panja to become the highest-grossing film in Nepal until Kabaddi 4: The Final Match surpassed it. The 4th Part of the series was announced in July 2022 with new ensemble cast with only Deepak Raj Giri, Kedar Ghimire, Deepa Shree Niraula and releases in 2024 on occasion if Dashain.",
  "profileImageUrl": "https://upload.wikimedia.org/wikipedia/en/4/4e/Chhakka_panja_three_ver2.jpg",
  "wikipediaUrl": "https://en.wikipedia.org/wiki/Chhakka_Panja_3",
  "dateOfBirth": "1996-11-08",
  "birthTime": "12:00:00",
  "birthCoordinatesLat": "28.705555555",
  "birthCoordinatesLng": "80.575",
  "moonSign": "6",
  "sunSign": "7",
  "lagnaSignText": "10",
  "planetaryCombinationIndex": null,
  "dataSource": "wikipedia_crawler",
  "isVerified": false,
  "categories": [
    "actor",
    "model"
  ],
  "qid": "Q57893456",
  "birthPlace": "Dhangadhi",
  "fetchedAt": "2026-04-07T16:43:35.983Z"
}