{
  "publicId": "890b4558",
  "wikipediaSlug": "Arvind_Sawant",
  "wikipediaId": "Q16890500",
  "name": "Arvind Sawant",
  "fullName": "Arvind Sawant",
  "profileSummary": "Arvind Ganpat Sawant is an Indian politician from the Shiv Sena (UBT) party who have served as Minister of Heavy Industries and Public Enterprises from 30 May 2019 to 11 November 2019. He is Member of Lok Sabha since 2014. On 11 November 2019, Sawant quit as union minister in Modi government due to ongoing power tussle between Bharatiya Janata Party and Shiv Sena in follow up to 2019 Maharashtra Legislative Assembly election.",
  "profileImageUrl": "https://upload.wikimedia.org/wikipedia/commons/thumb/0/07/Arvind_Sawant_%28cropped%29.jpg/330px-Arvind_Sawant_%28cropped%29.jpg",
  "wikipediaUrl": "https://en.wikipedia.org/wiki/Arvind_Sawant",
  "dateOfBirth": "1951-12-31",
  "birthTime": "12:00:00",
  "birthCoordinatesLat": "19.075833333",
  "birthCoordinatesLng": "72.8775",
  "moonSign": "10",
  "sunSign": "9",
  "lagnaSignText": "12",
  "planetaryCombinationIndex": null,
  "dataSource": "wikipedia_crawler",
  "isVerified": false,
  "categories": [
    "politician"
  ],
  "qid": "Q16890500",
  "birthPlace": "Mumbai",
  "fetchedAt": "2026-04-07T16:20:27.259Z"
}