{
  "publicId": "8d85a39a",
  "wikipediaSlug": "Siddaramaiah",
  "wikipediaId": "Q7508046",
  "name": "Siddaramaiah",
  "fullName": "Siddaramaiah",
  "profileSummary": "Siddaramaiah, also referred to by his nickname Siddu or Siddu Mama, is an Indian politician and lawyer who has served as the chief minister of Karnataka since May 2023. He had previously held that position from 2013 to 2018 for the first term being only the second person to complete a full five year term. In January 2026 he became the longest-serving chief minister of Karnataka, surpassing D. Devaraj Urs's record.",
  "profileImageUrl": "https://upload.wikimedia.org/wikipedia/commons/thumb/b/bc/The_Chief_Minister_of_Karnataka_Siddaramaiah_visits_PMO.jpg/330px-The_Chief_Minister_of_Karnataka_Siddaramaiah_visits_PMO.jpg",
  "wikipediaUrl": "https://en.wikipedia.org/wiki/Siddaramaiah",
  "dateOfBirth": "1948-08-12",
  "birthTime": "12:00:00",
  "birthCoordinatesLat": "12.21",
  "birthCoordinatesLng": "76.49",
  "moonSign": "8",
  "sunSign": "4",
  "lagnaSignText": "7",
  "planetaryCombinationIndex": null,
  "dataSource": "wikipedia_crawler",
  "isVerified": false,
  "categories": [
    "politician"
  ],
  "qid": "Q7508046",
  "birthPlace": "Mysuru district",
  "fetchedAt": "2026-04-07T16:36:57.961Z"
}