{
  "publicId": "e73f0f29",
  "wikipediaSlug": "Manraj_Ahluwalia",
  "wikipediaId": "Q15999762",
  "name": "List of Cambridge University Cricket Club players",
  "fullName": "List of Cambridge University Cricket Club players",
  "profileSummary": "This is a list in alphabetical order of cricketers who have played for Cambridge University Cricket Club (CUCC) in top-class matches since the club was established in 1820. Until 2020, a number of CUCC matches had first-class cricket status. In 1972 and 1974 the team also played official List A cricket matches.",
  "profileImageUrl": null,
  "wikipediaUrl": "https://en.wikipedia.org/wiki/List_of_Cambridge_University_Cricket_Club_players",
  "dateOfBirth": "1965-12-27",
  "birthTime": "12:00:00",
  "birthCoordinatesLat": "51.4666",
  "birthCoordinatesLng": "-0.3363",
  "moonSign": "11",
  "sunSign": "9",
  "lagnaSignText": "8",
  "planetaryCombinationIndex": null,
  "dataSource": "wikipedia_crawler",
  "isVerified": false,
  "categories": [
    "cricketer"
  ],
  "qid": "Q15999762",
  "birthPlace": "Isleworth",
  "fetchedAt": "2026-04-08T02:08:21.273Z"
}