{
  "publicId": "07c0b70e",
  "wikipediaSlug": "B._Y._Raghavendra",
  "wikipediaId": "Q24037",
  "name": "B. Y. Raghavendra",
  "fullName": "B. Y. Raghavendra",
  "profileSummary": "Bookanakere Yeddyurappa Raghavendra is an Indian politician and a member of the 16th Lok Sabha representing Shimoga district of Karnataka and was a member of 14th Karnataka Legislative Assembly. He previously represented Shikaripura Assembly constituency of Karnataka and is a member of the Bharatiya Janata Party (BJP).",
  "profileImageUrl": null,
  "wikipediaUrl": "https://en.wikipedia.org/wiki/B._Y._Raghavendra",
  "dateOfBirth": "1973-08-16",
  "birthTime": "12:00:00",
  "birthCoordinatesLat": "14.269722222",
  "birthCoordinatesLng": "75.356388888",
  "moonSign": "11",
  "sunSign": "4",
  "lagnaSignText": "7",
  "planetaryCombinationIndex": null,
  "dataSource": "wikipedia_crawler",
  "isVerified": false,
  "categories": [],
  "qid": "Q24037",
  "birthPlace": "Shikaripur",
  "fetchedAt": "2026-04-07T16:23:31.684Z"
}