{
  "publicId": "9e1df0e8",
  "wikipediaSlug": "Chhotelal_Kharwar",
  "wikipediaId": "Q16902103",
  "name": "Chhotelal Kharwar",
  "fullName": "Chhotelal Kharwar",
  "profileSummary": "Chhotelal Kharwar is a member of the Samajwadi Party. He won the 2014 Indian general elections from the Robertsganj constituency on a BJP ticket. He was a National Council member of the Bharatiya Janata Party from Sonbhadra. He recontested and won again in Robertsganj in the 2024 Indian general elections on a Samajwadi Party ticket.",
  "profileImageUrl": "https://upload.wikimedia.org/wikipedia/commons/e/ed/Chotelal_Kharwar_MP.jpg",
  "wikipediaUrl": "https://en.wikipedia.org/wiki/Chhotelal_Kharwar",
  "dateOfBirth": "1972-09-15",
  "birthTime": "12:00:00",
  "birthCoordinatesLat": "25.256944444",
  "birthCoordinatesLng": "83.267777777",
  "moonSign": "8",
  "sunSign": "5",
  "lagnaSignText": "8",
  "planetaryCombinationIndex": null,
  "dataSource": "wikipedia_crawler",
  "isVerified": false,
  "categories": [],
  "qid": "Q16902103",
  "birthPlace": "Chandauli",
  "fetchedAt": "2026-04-07T16:24:05.203Z"
}