{
  "publicId": "8ebcec42",
  "wikipediaSlug": "Farrhana_Bhatt",
  "wikipediaId": "Q136759063",
  "name": "Farrhana Bhatt",
  "fullName": "Farrhana Bhatt",
  "profileSummary": "Farrhana Bhatt is an Indian actress and social peace activist who primarily works in Hindi films, television and on streaming platforms. She is best known for her role as Jasmeet in Laila Majnu and for participating in Colors TV's reality show Bigg Boss 19 where she finished as the first Runner-up.",
  "profileImageUrl": "https://upload.wikimedia.org/wikipedia/commons/thumb/3/34/Farrhana_Bhatt_at_the_grand_finale_of_Bigg_Boss_19.jpg/330px-Farrhana_Bhatt_at_the_grand_finale_of_Bigg_Boss_19.jpg",
  "wikipediaUrl": "https://en.wikipedia.org/wiki/Farrhana_Bhatt",
  "dateOfBirth": "1997-01-01",
  "birthTime": "12:00:00",
  "birthCoordinatesLat": "34.091111111",
  "birthCoordinatesLng": "74.806111111",
  "moonSign": null,
  "sunSign": null,
  "lagnaSignText": null,
  "planetaryCombinationIndex": [
    "Manual_Sync_Required"
  ],
  "dataSource": "wikipedia_crawler",
  "isVerified": false,
  "categories": [
    "actor"
  ],
  "qid": "Q136759063",
  "birthPlace": "Srinagar",
  "fetchedAt": "2026-04-07T12:19:18.547Z"
}