{
  "publicId": "48efa501",
  "wikipediaSlug": "Bimalendra_Nidhi",
  "wikipediaId": "Q4913693",
  "name": "Bimalendra Nidhi",
  "fullName": "Bimalendra Nidhi",
  "profileSummary": "Bimalendra Nidhi is a Nepali politician who previously served as a Deputy Prime Minister and Home Minister of Nepal. Also a former Minister of Physical Infrastructure and Transport, Nidhi has won from Dhanusha 3 as MP of House of Representatives and Constituent Assembly. Nidhi has also served as the Vice-president and General secretary of Nepali Congress.",
  "profileImageUrl": "https://upload.wikimedia.org/wikipedia/commons/thumb/d/da/The_Deputy_Prime_Minister_and_Home_Minister_of_Nepal%2C_Shri_Bimalendra_Nidhi.jpg/330px-The_Deputy_Prime_Minister_and_Home_Minister_of_Nepal%2C_Shri_Bimalendra_Nidhi.jpg",
  "wikipediaUrl": "https://en.wikipedia.org/wiki/Bimalendra_Nidhi",
  "dateOfBirth": "1956-09-25",
  "birthTime": "12:00:00",
  "birthCoordinatesLat": "26.712222222",
  "birthCoordinatesLng": "85.921666666",
  "moonSign": null,
  "sunSign": null,
  "lagnaSignText": null,
  "planetaryCombinationIndex": [
    "Manual_Sync_Required"
  ],
  "dataSource": "wikipedia_crawler",
  "isVerified": false,
  "categories": [
    "politician"
  ],
  "qid": "Q4913693",
  "birthPlace": "Janakpurdham",
  "fetchedAt": "2026-04-07T16:53:00.569Z"
}