{
  "publicId": "d90f7348",
  "wikipediaSlug": "Chautariya_Pushkar_Shah",
  "wikipediaId": "Q5088375",
  "name": "Chautariya Pushkar Shah",
  "fullName": "Chautariya Pushkar Shah",
  "profileSummary": "Mukhtiyar General Sri Sri Sri Chautariya Pushkar Shah was a prominent Nepalese statesman, diplomat, and military leader. He served as Mukhtiyar of Nepal from August 1838 to early 1839. He is notable for his diplomatic missions to China and for attempting to establish strategic alliances with regional powers to protect Nepal’s sovereignty during the early 19th century.",
  "profileImageUrl": "https://upload.wikimedia.org/wikipedia/commons/5/5f/Puskar_Shah.jpg",
  "wikipediaUrl": "https://en.wikipedia.org/wiki/Chautariya_Pushkar_Shah",
  "dateOfBirth": "1784-08-16",
  "birthTime": "12:00:00",
  "birthCoordinatesLat": "27.71",
  "birthCoordinatesLng": "85.32",
  "moonSign": null,
  "sunSign": null,
  "lagnaSignText": null,
  "planetaryCombinationIndex": [
    "Manual_Sync_Required"
  ],
  "dataSource": "wikipedia_crawler",
  "isVerified": false,
  "categories": [
    "politician"
  ],
  "qid": "Q5088375",
  "birthPlace": "Kathmandu",
  "fetchedAt": "2026-04-07T16:55:11.205Z"
}